ElkstackZhongwenZhinan/README.md
ElkstackZhongwenZhinan/__init__.py
ElkstackZhongwenZhinan/__main__.py
ElkstackZhongwenZhinan/file.epub
ElkstackZhongwenZhinan/index.html
ElkstackZhongwenZhinan/css/__init__.py
ElkstackZhongwenZhinan/css/annotations.css
ElkstackZhongwenZhinan/css/main.css
ElkstackZhongwenZhinan/css/normalize.css
ElkstackZhongwenZhinan/css/popup.css
ElkstackZhongwenZhinan/font/__init__.py
ElkstackZhongwenZhinan/font/fontello.eot
ElkstackZhongwenZhinan/font/fontello.svg
ElkstackZhongwenZhinan/font/fontello.ttf
ElkstackZhongwenZhinan/font/fontello.woff
ElkstackZhongwenZhinan/img/__init__.py
ElkstackZhongwenZhinan/img/annotator-glyph-sprite.png
ElkstackZhongwenZhinan/img/annotator-icon-sprite.png
ElkstackZhongwenZhinan/img/apple-touch-icon.png
ElkstackZhongwenZhinan/img/cancelfullscreen.png
ElkstackZhongwenZhinan/img/close.png
ElkstackZhongwenZhinan/img/fullscreen.png
ElkstackZhongwenZhinan/img/loader.gif
ElkstackZhongwenZhinan/img/menu-icon.png
ElkstackZhongwenZhinan/img/save.png
ElkstackZhongwenZhinan/img/saved.png
ElkstackZhongwenZhinan/img/settings-s.png
ElkstackZhongwenZhinan/img/settings.png
ElkstackZhongwenZhinan/img/star.png
ElkstackZhongwenZhinan/js/__init__.py
ElkstackZhongwenZhinan/js/epub.js
ElkstackZhongwenZhinan/js/epub.min.js
ElkstackZhongwenZhinan/js/epub.min.map
ElkstackZhongwenZhinan/js/hooks.min.js
ElkstackZhongwenZhinan/js/hooks.min.map
ElkstackZhongwenZhinan/js/reader.js
ElkstackZhongwenZhinan/js/reader.js.map
ElkstackZhongwenZhinan/js/reader.min.js
ElkstackZhongwenZhinan/js/reader.min.map
ElkstackZhongwenZhinan/js/hooks/__init__.py
ElkstackZhongwenZhinan/js/hooks/extensions/__init__.py
ElkstackZhongwenZhinan/js/hooks/extensions/highlight.js
ElkstackZhongwenZhinan/js/libs/__init__.py
ElkstackZhongwenZhinan/js/libs/jquery.min.js
ElkstackZhongwenZhinan/js/libs/localforage.min.js
ElkstackZhongwenZhinan/js/libs/screenfull.js
ElkstackZhongwenZhinan/js/libs/screenfull.min.js
ElkstackZhongwenZhinan/js/libs/zip.min.js
elkstack_zhongwen_zhinan-2024.3.1.0.dist-info/METADATA
elkstack_zhongwen_zhinan-2024.3.1.0.dist-info/WHEEL
elkstack_zhongwen_zhinan-2024.3.1.0.dist-info/entry_points.txt
elkstack_zhongwen_zhinan-2024.3.1.0.dist-info/top_level.txt
elkstack_zhongwen_zhinan-2024.3.1.0.dist-info/RECORD
